{"stats":{"minecraft:crafted":{"minecraft:iron_leggings":4,"minecraft:iron_boots":4,"minecraft:iron_chestplate":4,"minecraft:iron_helmet":4},"minecraft:mined":{"minecraft:deepslate_tiles":2,"minecraft:blackstone":28,"minecraft:tinted_glass":2,"minecraft:basalt":3,"minecraft:netherrack":62,"minecraft:sugar_cane":64},"minecraft:custom":{"minecraft:open_enderchest":2,"minecraft:open_chest":22,"minecraft:time_since_rest":2887,"minecraft:open_shulker_box":10,"minecraft:crouch_one_cm":101,"minecraft:play_time":10241,"minecraft:sprint_one_cm":62728,"minecraft:walk_one_cm":26458,"minecraft:deaths":1,"minecraft:sneak_time":555,"minecraft:trigger_trapped_chest":2,"minecraft:walk_under_water_one_cm":10199,"minecraft:jump":59,"minecraft:inspect_hopper":3,"minecraft:leave_game":5,"minecraft:time_since_death":2862,"minecraft:walk_on_water_one_cm":2737,"minecraft:total_world_time":10241,"minecraft:damage_taken":230,"minecraft:swim_one_cm":13197,"minecraft:interact_with_crafting_table":3,"minecraft:fall_one_cm":2316,"minecraft:fly_one_cm":19015},"minecraft:picked_up":{"minecraft:iron_chestplate":3,"minecraft:iron_leggings":3,"minecraft:basalt":3,"minecraft:blackstone":28,"minecraft:diamond_chestplate":1,"minecraft:deepslate_tiles":4,"minecraft:iron_helmet":3,"minecraft:iron_ingot":160,"minecraft:diamond_helmet":1,"minecraft:tinted_glass":4,"minecraft:netherrack":58,"minecraft:sugar_cane":242,"minecraft:iron_boots":3,"minecraft:diamond_pickaxe":1},"minecraft:used":{"minecraft:diamond_pickaxe":97}},"DataVersion":2730}